Metadata-Version: 1.0
Name: proba-distributions
Version: 0.1
Summary: Gaussian and Binomial distributions
Home-page: UNKNOWN
Author: Neeha Rathna Janjanam
Author-email: samy1541998@gmail.com
License: UNKNOWN
Platform: UNKNOWN
